more_click/__init__.py
more_click/options.py
more_click/version.py
more_click/web.py
more_click-0.1.1.dist-info/LICENSE
more_click-0.1.1.dist-info/METADATA
more_click-0.1.1.dist-info/WHEEL
more_click-0.1.1.dist-info/top_level.txt
more_click-0.1.1.dist-info/RECORD
